dareplane_utils/default_server/__init__.py
dareplane_utils/default_server/functions.py
dareplane_utils/default_server/server.py
dareplane_utils/general/event_loop.py
dareplane_utils/general/ringbuffer.py
dareplane_utils/general/time.py
dareplane_utils/logging/logger.py
dareplane_utils/logging/server.py
dareplane_utils/logging/ujson_socket_handler.py
dareplane_utils/signal_processing/filtering.py
dareplane_utils/stream_watcher/lsl_stream_watcher.py
dareplane_utils-0.0.16.dist-info/licenses/LICENSE
dareplane_utils-0.0.16.dist-info/METADATA
dareplane_utils-0.0.16.dist-info/WHEEL
dareplane_utils-0.0.16.dist-info/top_level.txt
dareplane_utils-0.0.16.dist-info/RECORD
