Metadata-Version: 2.4
Name: dareplane_utils
Version: 0.0.16
Summary: Default utilities for the dareplane platform
Author-email: Matthias Dold <matthias.dold@gmx.net>
Project-URL: homepage, https://github.com/matthiasdold/dareplane-pyutils
Requires-Python: >=3.10
License-File: LICENSE
Requires-Dist: colorlog>=6.8.2
Requires-Dist: contourpy>=1.2.1
Requires-Dist: coverage>=7.5.3
Requires-Dist: cycler>=0.12.1
Requires-Dist: fonttools>=4.53.0
Requires-Dist: iniconfig>=2.0.0
Requires-Dist: kiwisolver>=1.4.5
Requires-Dist: matplotlib>=3.9.0
Requires-Dist: numpy>=1.26.4
Requires-Dist: packaging>=24.0
Requires-Dist: pillow>=10.3.0
Requires-Dist: pluggy>=1.5.0
Requires-Dist: psutil>=5.9.8
Requires-Dist: pylsl>=1.16.2
Requires-Dist: pyparsing>=3.1.2
Requires-Dist: pytest>=8.2.2
Requires-Dist: python-dateutil>=2.9.0
Requires-Dist: scipy>=1.13.1
Requires-Dist: six>=1.16.0
Requires-Dist: ujson>=5.10.0
Requires-Dist: xmltodict>=0.13.0
Dynamic: license-file
